monolish_log_viewer/__init__.py
monolish_log_viewer/__main__.py
monolish_log_viewer/aggregate.py
monolish_log_viewer/command_manager.py
monolish_log_viewer/create_log.py
monolish_log_viewer/debug.py
monolish_log_viewer/drop_information.py
monolish_log_viewer/formats.py
monolish_log_viewer/html.py
monolish_log_viewer/read.py
monolish_log_viewer-0.1.1.dist-info/entry_points.txt
monolish_log_viewer-0.1.1.dist-info/WHEEL
monolish_log_viewer-0.1.1.dist-info/METADATA
monolish_log_viewer-0.1.1.dist-info/RECORD
