Metadata-Version: 2.1
Name: monolish-log-viewer
Version: 0.1.1
Summary: Logger script
License: Apache-2.0
Author: RICOS Co. Ltd.
Requires-Python: >=3.7.9,<4.0.0
Classifier: License :: OSI Approved :: Apache Software License
Classifier: Programming Language :: Python :: 3
Classifier: Programming Language :: Python :: 3.8
Classifier: Programming Language :: Python :: 3.9
Requires-Dist: PyYAML (>=5.2,<6.0)
Requires-Dist: argparse (>=1.4.0,<2.0.0)
Requires-Dist: numpy (>=1.17,<2.0)
Requires-Dist: pandas (>=1.0,<2.0)
